README.md
setup.py
global_chem/__init__.py
global_chem/__main__.py
global_chem/cli.py
global_chem/global_chem.py
global_chem.egg-info/PKG-INFO
global_chem.egg-info/SOURCES.txt
global_chem.egg-info/dependency_links.txt
global_chem.egg-info/not-zip-safe
global_chem.egg-info/requires.txt
global_chem.egg-info/top_level.txt
global_chem/animals/__init__.py
global_chem/animals/insects/__init__.py
global_chem/animals/insects/insect_sex_pheromones.py
global_chem/animals/snakes/__init__.py
global_chem/animals/snakes/drugs_from_snake_venom.py
global_chem/education/__init__.py
global_chem/education/cengage/__init__.py
global_chem/education/cengage/organic_and_inorganic_bronsted_acids.py
global_chem/environment/__init__.py
global_chem/environment/alternative_jet_fuels.py
global_chem/environment/chemicals_from_biomass.py
global_chem/environment/emerging_perfluoroalkyls.py
global_chem/food/__init__.py
global_chem/food/color_additives/__init__.py
global_chem/food/color_additives/fda_list_five.py
global_chem/food/color_additives/fda_list_four.py
global_chem/food/color_additives/fda_list_one.py
global_chem/food/color_additives/fda_list_seven.py
global_chem/food/color_additives/fda_list_six.py
global_chem/food/color_additives/fda_list_three.py
global_chem/food/color_additives/fda_list_two.py
global_chem/food/fruits/__init__.py
global_chem/food/fruits/mango/__init__.py
global_chem/food/fruits/mango/mango_amino_acids.py
global_chem/food/fruits/mango/mango_fatty_acids.py
global_chem/food/fruits/mango/mango_flavonoids.py
global_chem/food/fruits/mango/mango_phenolic_acids.py
global_chem/food/fruits/mango/mango_phyto_compounds.py
global_chem/food/fruits/mango/mango_vitamins.py
global_chem/food/salt/__init__.py
global_chem/food/salt/salt.py
global_chem/formulation/__init__.py
global_chem/formulation/excipients/__init__.py
global_chem/formulation/excipients/allergen_inactive_ingredients.py
global_chem/formulation/excipients/biopharmaceutics_class_three/__init__.py
global_chem/formulation/excipients/biopharmaceutics_class_three/cimetidine_and_acyclovir.py
global_chem/formulation/excipients/monoclonal_antibodies/__init__.py
