Metadata-Version: 2.1
Name: global-chem
Version: 1.10.0
Summary: UNKNOWN
Home-page: https://www.github.com/Sulstice/global-chem
Author: Suliman Sharif
Author-email: sharifsuliman1@gmail.com
License: MPL 2.0
Keywords: smiles molecules chemistry organic iupac
Platform: UNKNOWN
Classifier: Development Status :: 4 - Beta
Classifier: Natural Language :: English
Classifier: License :: OSI Approved :: Mozilla Public License 2.0 (MPL 2.0)
Classifier: Intended Audience :: Developers
Classifier: Programming Language :: Python :: 3
Classifier: Programming Language :: Python :: 3.3
Classifier: Programming Language :: Python :: 3.4
Classifier: Programming Language :: Python :: 3.5
Classifier: Programming Language :: Python :: 3.6
Classifier: Programming Language :: Python :: 3.7
Classifier: Programming Language :: Python :: 3.8
Classifier: Programming Language :: Python :: 3.9
Classifier: Programming Language :: Python :: 3.10
Classifier: Programming Language :: Python :: 3.11
Provides-Extra: all
Provides-Extra: bioinformatics
Provides-Extra: cheminformatics
Provides-Extra: development_operations
Provides-Extra: forcefields
Provides-Extra: graphing
Provides-Extra: quantum_chemistry
